paiagym/__init__.py
paiagym/arguments.py
paiagym/config.py
paiagym/game.py
paiagym/inferencing.py
paiagym/main.py
paiagym/manage.py
paiagym/training.py
paiagym/utils.py
paiagym/wrapper.py
paiagym-0.0.4.dist-info/METADATA
paiagym-0.0.4.dist-info/WHEEL
paiagym-0.0.4.dist-info/entry_points.txt
paiagym-0.0.4.dist-info/licenses/LICENSE
paiagym-0.0.4.dist-info/RECORD
