Metadata-Version: 2.1
Name: paiagym
Version: 0.0.4
Summary: A platform to run Gymnasium or PettingZoo games with AI.
Project-URL: Homepage, https://github.com/PAIA-Playful-AI-Arena/paiagym
Project-URL: Bug Tracker, https://github.com/PAIA-Playful-AI-Arena/paiagym/issues
Author-email: timcsy <timocsy@yahoo.com.tw>
License-File: LICENSE
Classifier: License :: OSI Approved :: MIT License
Classifier: Operating System :: OS Independent
Classifier: Programming Language :: Python :: 3
Requires-Python: >=3.8
Requires-Dist: gymize==0.0.2
Requires-Dist: python-dotenv
Requires-Dist: requests
Requires-Dist: stable-baselines3
